quiper/__init__.py
quiper/__main__.py
quiper/_version.py
quiper/app.py
quiper/constants.py
quiper/launcher.py
quiper/listener.py
quiper/main.py
quiper/settings.py
quiper/templates.py
quiper/logo/icon.icns
quiper/logo/logo.png
quiper-0.1.2.dist-info/METADATA
quiper-0.1.2.dist-info/WHEEL
quiper-0.1.2.dist-info/entry_points.txt
quiper-0.1.2.dist-info/licenses/LICENSE
quiper-0.1.2.dist-info/RECORD
