Metadata-Version: 2.4
Name: quiper
Version: 0.1.2
Summary: A macOS overlay for AI web applications, providing a floating window with a web view and hotkey support.
Author-email: Sassan Haradji <me@sassanh.com>
Maintainer-email: Sassan Haradji <me@sassanh.com>
License-Expression: MIT
License-File: LICENSE
Keywords: ai,chatgpt,gemini,grok,hotkey,macos,ollama,overlay,webview
Requires-Python: >=3.12
Requires-Dist: jaraco-text>=4.0.0
Requires-Dist: pyobjc-framework-applicationservices>=11.1
Requires-Dist: pyobjc-framework-quartz>=11.1
Requires-Dist: pyobjc-framework-webkit>=11.1
Requires-Dist: quickmachotkey>=2025.7.28
